antsibull_core/__init__.py
antsibull_core/ansible_core.py
antsibull_core/app_context.py
antsibull_core/args.py
antsibull_core/collection_meta.py
antsibull_core/collections.py
antsibull_core/compat.py
antsibull_core/config.py
antsibull_core/dependency_files.py
antsibull_core/filesystem.py
antsibull_core/galaxy.py
antsibull_core/logging.py
antsibull_core/py.typed
antsibull_core/pydantic.py
antsibull_core/subprocess_util.py
antsibull_core/tarball.py
antsibull_core/venv.py
antsibull_core/yaml.py
antsibull_core/schemas/__init__.py
antsibull_core/schemas/collection_meta.py
antsibull_core/schemas/config.py
antsibull_core/schemas/context.py
antsibull_core/schemas/validators.py
antsibull_core/utils/__init__.py
antsibull_core/utils/collections.py
antsibull_core/utils/hashing.py
antsibull_core/utils/http.py
antsibull_core/utils/io.py
antsibull_core/vendored/__init__.py
antsibull_core/vendored/_argparse_booleanoptionalaction.py
antsibull_core/vendored/collections.py
antsibull_core/vendored/json_utils.py
antsibull_core-3.3.0.dist-info/METADATA
antsibull_core-3.3.0.dist-info/WHEEL
antsibull_core-3.3.0.dist-info/licenses/LICENSES/BSD-2-Clause.txt
antsibull_core-3.3.0.dist-info/licenses/LICENSES/GPL-3.0-or-later.txt
antsibull_core-3.3.0.dist-info/licenses/LICENSES/MIT.txt
antsibull_core-3.3.0.dist-info/licenses/LICENSES/PSF-2.0.txt
antsibull_core-3.3.0.dist-info/RECORD
