Metadata-Version: 2.3
Name: antsibull-core
Version: 3.3.0
Summary: Tools for building the Ansible Distribution
Project-URL: Source code, https://github.com/ansible-community/antsibull-core
Project-URL: Code of Conduct, https://docs.ansible.com/ansible/latest/community/code_of_conduct.html
Project-URL: Bug tracker, https://github.com/ansible-community/antsibull-core/issues
Author-email: Toshio Kuratomi <a.badger@gmail.com>, Felix Fontein <felix@fontein.de>
Maintainer-email: Felix Fontein <felix@fontein.de>, Maxwell G <maxwell@gtmx.me>
License-Expression: GPL-3.0-or-later AND BSD-2-Clause AND MIT AND PSF-2.0
License-File: LICENSES/BSD-2-Clause.txt
License-File: LICENSES/GPL-3.0-or-later.txt
License-File: LICENSES/MIT.txt
License-File: LICENSES/PSF-2.0.txt
Classifier: Development Status :: 4 - Beta
Classifier: Framework :: Ansible
Classifier: Intended Audience :: Developers
Classifier: Programming Language :: Python :: 3
Classifier: Programming Language :: Python :: 3.9
Classifier: Programming Language :: Python :: 3.10
Classifier: Programming Language :: Python :: 3.11
Classifier: Programming Language :: Python :: 3.12
Classifier: Typing :: Typed
Requires-Python: >=3.9
Requires-Dist: aiofiles
Requires-Dist: aiohttp>=3.3.0
Requires-Dist: antsibull-fileutils<2.0.0,>=1.0.0
Requires-Dist: build
Requires-Dist: packaging>=20.0
Requires-Dist: perky
Requires-Dist: pydantic~=2.0
Requires-Dist: semantic-version
Requires-Dist: twiggy>=0.5.0
Provides-Extra: codeqa
Requires-Dist: antsibull-changelog; extra == 'codeqa'
Requires-Dist: flake8>=6.0.0; extra == 'codeqa'
Requires-Dist: pylint>=2.15.7; extra == 'codeqa'
Requires-Dist: reuse; extra == 'codeqa'
Provides-Extra: coverage
Requires-Dist: coverage[toml]; extra == 'coverage'
Provides-Extra: dev
Requires-Dist: antsibull-changelog; extra == 'dev'
Requires-Dist: asynctest; extra == 'dev'
Requires-Dist: black>=24; extra == 'dev'
Requires-Dist: coverage[toml]; extra == 'dev'
Requires-Dist: cryptography; extra == 'dev'
Requires-Dist: flake8>=6.0.0; extra == 'dev'
Requires-Dist: isort; extra == 'dev'
Requires-Dist: mypy; extra == 'dev'
Requires-Dist: nox; extra == 'dev'
Requires-Dist: pylint>=2.15.7; extra == 'dev'
Requires-Dist: pyre-check>=0.9.17; extra == 'dev'
Requires-Dist: pytest; extra == 'dev'
Requires-Dist: pytest-asyncio>=0.20; extra == 'dev'
Requires-Dist: pytest-cov; extra == 'dev'
Requires-Dist: pytest-error-for-skips; extra == 'dev'
Requires-Dist: reuse; extra == 'dev'
Requires-Dist: types-aiofiles; extra == 'dev'
Requires-Dist: typing-extensions; extra == 'dev'
Provides-Extra: formatters
Requires-Dist: black>=24; extra == 'formatters'
Requires-Dist: isort; extra == 'formatters'
Provides-Extra: test
Requires-Dist: asynctest; extra == 'test'
Requires-Dist: cryptography; extra == 'test'
Requires-Dist: pytest; extra == 'test'
Requires-Dist: pytest-asyncio>=0.20; extra == 'test'
Requires-Dist: pytest-cov; extra == 'test'
Requires-Dist: pytest-error-for-skips; extra == 'test'
Provides-Extra: typing
Requires-Dist: mypy; extra == 'typing'
Requires-Dist: pyre-check>=0.9.17; extra == 'typing'
Requires-Dist: types-aiofiles; extra == 'typing'
Requires-Dist: typing-extensions; extra == 'typing'
